get_once/__init__.py
get_once/mixins.py
django_get_once-1.0.0.dist-info/LICENCE
django_get_once-1.0.0.dist-info/METADATA
django_get_once-1.0.0.dist-info/WHEEL
django_get_once-1.0.0.dist-info/top_level.txt
django_get_once-1.0.0.dist-info/RECORD
